LICENSE.md
MANIFEST.in
README.md
pyproject.toml
llama_cpp/__init__.py
llama_cpp/_utils.py
llama_cpp/libllama.so
llama_cpp/libllava.so
llama_cpp/llama.py
llama_cpp/llama_chat_format.py
llama_cpp/llama_cpp.py
llama_cpp/llama_grammar.py
llama_cpp/llama_types.py
llama_cpp/llava_cpp.py
llama_cpp/py.typed
llama_cpp/server/__init__.py
llama_cpp/server/__main__.py
llama_cpp/server/app.py
llama_cpp/server/cli.py
llama_cpp/server/errors.py
llama_cpp/server/model.py
llama_cpp/server/settings.py
llama_cpp/server/types.py
llama_cpp_python_binary.egg-info/PKG-INFO
llama_cpp_python_binary.egg-info/SOURCES.txt
llama_cpp_python_binary.egg-info/dependency_links.txt
llama_cpp_python_binary.egg-info/requires.txt
llama_cpp_python_binary.egg-info/top_level.txt
tests/test_grammar.py
tests/test_llama.py