Metadata-Version: 2.1
Name: llama_cpp_python_binary
Version: 0.2.26
Summary: Python bindings for the llama.cpp library
Author-email: Andrei Betlen <abetlen@gmail.com>
License: MIT
Project-URL: Homepage, https://github.com/grantjenks/llama-cpp-python-binary
Project-URL: Issues, https://github.com/grantjenks/llama-cpp-python-binary/issues
Project-URL: Documentation, https://github.com/grantjenks/llama-cpp-python-binary
Project-URL: Changelog, https://github.com/grantjenks/llama-cpp-python-binary
Classifier: Programming Language :: Python :: 3
Classifier: Programming Language :: Python :: 3.8
Classifier: Programming Language :: Python :: 3.9
Classifier: Programming Language :: Python :: 3.10
Classifier: Programming Language :: Python :: 3.11
Classifier: Programming Language :: Python :: 3.12
Requires-Python: >=3.8
License-File: LICENSE.md
Requires-Dist: typing-extensions>=4.5.0
Requires-Dist: numpy>=1.20.0
Requires-Dist: diskcache>=5.6.1
Requires-Dist: uvicorn>=0.22.0
Requires-Dist: fastapi>=0.100.0
Requires-Dist: pydantic-settings>=2.0.1
Requires-Dist: sse-starlette>=1.6.1
Requires-Dist: starlette-context<0.4,>=0.3.6
Provides-Extra: test
Requires-Dist: pytest>=7.4.0; extra == "test"
Requires-Dist: httpx>=0.24.1; extra == "test"
Requires-Dist: scipy>=1.10; extra == "test"
Provides-Extra: dev
Requires-Dist: black>=23.3.0; extra == "dev"
Requires-Dist: twine>=4.0.2; extra == "dev"
Requires-Dist: mkdocs>=1.4.3; extra == "dev"
Requires-Dist: mkdocstrings[python]>=0.22.0; extra == "dev"
Requires-Dist: mkdocs-material>=9.1.18; extra == "dev"
Requires-Dist: pytest>=7.4.0; extra == "dev"
Requires-Dist: httpx>=0.24.1; extra == "dev"
Provides-Extra: all
Requires-Dist: llama_cpp_python[dev,server,test]; extra == "all"
